unUsefull/__init__.py
unUsefull-0.0.3.dist-info/LICENSE
unUsefull-0.0.3.dist-info/METADATA
unUsefull-0.0.3.dist-info/WHEEL
unUsefull-0.0.3.dist-info/top_level.txt
unUsefull-0.0.3.dist-info/RECORD
